<?xml version="1.0" encoding="UTF-8"?><scores>
















    


<score><date>18/11/2015 21:2</date><game>TicTacToe</game><computerScore>x</computerScore><userScore>x</userScore><playerName>some</playerName></score><score><date>18/11/2015 21:14</date><game>Snake</game><computerScore>x</computerScore><userScore>0</userScore><playerName>some</playerName></score><score><date>18/11/2015 21:14</date><game>Snake</game><computerScore>x</computerScore><userScore>1</userScore><playerName>some</playerName></score><score><date>18/11/2015 21:14</date><game>Snake</game><computerScore>x</computerScore><userScore>0</userScore><playerName>some</playerName></score><score><date>18/11/2015 21:14</date><game>Snake</game><computerScore>x</computerScore><userScore>0</userScore><playerName>some</playerName></score><score><date>18/11/2015 21:14</date><game>Snake</game><computerScore>x</computerScore><userScore>0</userScore><playerName>some</playerName></score><score><date>18/11/2015 21:14</date><game>Snake</game><computerScore>x</computerScore><userScore>0</userScore><playerName>some</playerName></score><score><date>18/11/2015 21:14</date><game>Snake</game><computerScore>x</computerScore><userScore>0</userScore><playerName>some</playerName></score><score><date>18/11/2015 21:14</date><game>Snake</game><computerScore>x</computerScore><userScore>0</userScore><playerName>some</playerName></score><score><date>18/11/2015 21:15</date><game>Snake</game><computerScore>x</computerScore><userScore>0</userScore><playerName>some</playerName></score></scores>