<?xml version="1.0" encoding="UTF-8"?><messages>
   
<recieved>
    <text>Recieved message text here</text>
    <user>UserNameHere</user>
    <date>01/30/2015</date>
</recieved>

<recieved>
    <text>Recieved message text here</text>
    <user>UserNameHere</user>
    <date>03/20/2015</date>
</recieved>

<recieved>
    <text>Recieved message text here</text>
    <user>UserNameHere</user>
    <date>02/30/2015</date>
</recieved>

<sent>
    <text>Sent message text here</text>
    <user>UserNameHere</user>
    <date>01/20/2015</date>
</sent>
    
<sent><text>Hey info, how are You?</text><user>info@info.com</user><date>000</date></sent><sent><text>Your Message Here</text><user>mmmm</user><date>7/11 time: 22:36</date></sent><sent><text>Your Message Here</text><user>mmmm</user><date>7/11/2015 22:37</date></sent><sent><text>Hey, how are you?</text><user>mmmm</user><date>8/11/2015 15:24</date></sent><sent><text>Hey querty, how are you?</text><user>qwerty</user><date>8/11/2015 15:24</date></sent></messages>